{
    "Language": "Bahasa Indonesia",
    "htmlLangAtt": "id",
    "h1": "Safevideokit.com - Cara paling aman untuk memproses video Anda",
    "h2": "Tidak ada file yang dikirim ke server. 100% aman.",
    "title": "Safevideokit.com - Cara paling aman untuk memproses video Anda",
    "TITLE": "Safevideokit.com - Cara paling aman untuk memproses video Anda",
    "meta": "Alat editor video online kami benar-benar gratis dan mudah digunakan. Kami memastikan semua data Anda aman saat Anda mengedit video Anda. Kami mendukung berbagai macam format video seperti mp3, mov, mkv dll",
    "keywords": "key1,key2,key3,key4",
    "features": [
        {
            "name": "Tanaman MP4",
            "description": "Pangkas semua video MP4",
            "color": "#3867d6",
            "icon": "/assets/FeatureIcons/crop.svg",
            "url": "/id/crop-mp4"
        },
        {
            "name": "Pangkas video",
            "description": "Pangkas video apa pun",
            "color": "#ff5e57",
            "icon": "/assets/FeatureIcons/crop.svg",
            "url": "/id/crop-video"
        },
        {
            "name": "Penyunting MP4",
            "description": "Mengedit video MP4",
            "color": "#4bcffa",
            "icon": "/assets/FeatureIcons/edit.svg",
            "url": "/id/edit-mp4-video"
        },
        {
            "name": "Video Balik",
            "description": "Balik video apa pun",
            "color": "#ff615c",
            "icon": "/assets/FeatureIcons/flip.svg",
            "url": "/id/flip-video"
        },
        {
            "name": "Kompresor MOV",
            "description": "Kompres setiap video MOV",
            "color": "#0be881",
            "icon": "/assets/FeatureIcons/compress.svg",
            "url": "/id/mov-compressor"
        },
        {
            "name": "MP4 kompresor",
            "description": "Kompres semua video MP4",
            "color": "#c56cf0",
            "icon": "/assets/FeatureIcons/compress.svg",
            "url": "/id/mp4-compressor"
        },
        {
            "name": "Pemotong MP4",
            "description": "Potong video MP4",
            "color": "#7d5fff",
            "icon": "/assets/FeatureIcons/split.svg",
            "url": "/id/mp4-cutter"
        },
        {
            "name": "Editor Video",
            "description": "Mengedit video apa pun",
            "color": "#ffa502",
            "icon": "/assets/FeatureIcons/edit.svg",
            "url": "/id/video-editor"
        },
        {
            "name": "MP4 pemangkas",
            "description": "Memangkas video MP4",
            "color": "#4cd137",
            "icon": "/assets/FeatureIcons/split.svg",
            "url": "/id/mp4-trimmer"
        },
        {
            "name": "Ubah ukuran video",
            "description": "Ubah ukuran video apa pun",
            "color": "#ff793f",
            "icon": "/assets/FeatureIcons/resize.svg",
            "url": "/id/resize-video"
        },
        {
            "name": "Kompresor video",
            "description": "Kompres video apa pun",
            "color": "#9c88ff",
            "icon": "/assets/FeatureIcons/compress.svg",
            "url": "/id/video-compressor"
        },
        {
            "name": "Pemotong Video",
            "description": "Potong video apa pun",
            "color": "#ff615c",
            "icon": "/assets/FeatureIcons/split.svg",
            "url": "/id/video-cutter"
        },
        {
            "name": "Pemutar video",
            "description": "Putar video apa pun",
            "color": "#33d9b2",
            "icon": "/assets/FeatureIcons/rotate.svg",
            "url": "/id/video-rotater"
        },
        {
            "name": "Video splitter",
            "description": "Membagi setiap video",
            "color": "#e84118",
            "icon": "/assets/FeatureIcons/split.svg",
            "url": "/id/video-splitter"
        },
        {
            "name": "Video pemangkas",
            "description": "Potong video apapun",
            "color": "#00a8ff",
            "icon": "/assets/FeatureIcons/split.svg",
            "url": "/id/video-trimmer"
        },
        {
            "name": "Ekstrak audio",
            "description": "Ekstrak audio dari video",
            "color": "#26de81",
            "icon": "/assets/FeatureIcons/sound.svg",
            "url": "/id/extract-audio"
        },
        {
            "name": "Tambahkan sub judul ke MP4",
            "description": "Tambahkan subtitle ke video MP4",
            "color": "#BD7ED8",
            "icon": "/assets/FeatureIcons/subtitle.svg",
            "url": "/id/subtitle-mp4"
        },
        {
            "name": "Ubah Ukuran Untuk Facebook",
            "description": "Ubah Ukuran Video Untuk Facebook",
            "color": "#1773EA",
            "icon": "/assets/FeatureIcons/facebook.svg",
            "url": "/id/resize-for-facebook"
        },
        {
            "name": "Ubah Ukuran Untuk Instagram",
            "description": "Ubah Ukuran Video Untuk Instagram",
            "color": "#F00075",
            "icon": "/assets/FeatureIcons/instagram.svg",
            "url": "/id/resize-for-instagram"
        },
        {
            "name": "Ubah Ukuran Untuk LinkedIn",
            "description": "Ubah Ukuran Video Untuk LinkedIn",
            "color": "#0A66C2",
            "icon": "/assets/FeatureIcons/linkedin.svg",
            "url": "/id/resize-for-linkedin"
        },
        {
            "name": "Ubah Ukuran Untuk Pinterest",
            "description": "Ubah Ukuran Video Untuk Pinterest",
            "color": "#BD081C",
            "icon": "/assets/FeatureIcons/pinterest.svg",
            "url": "/id/resize-for-pinterest"
        },
        {
            "name": "Ubah Ukuran Untuk Snapchat",
            "description": "Ubah Ukuran Video Untuk Snapchat",
            "color": "#9999FF",
            "icon": "/assets/FeatureIcons/snapchat.svg",
            "url": "/id/resize-for-snapchat"
        },
        {
            "name": "Ubah Ukuran Untuk Tiktok",
            "description": "Ubah Ukuran Video Untuk Tiktok",
            "color": "#D44638",
            "icon": "/assets/FeatureIcons/tiktok.svg",
            "url": "/id/resize-for-tiktok"
        },
        {
            "name": "Ubah Ukuran Untuk Twitter",
            "description": "Ubah Ukuran Video Untuk Twitter",
            "color": "#1DA1F2",
            "icon": "/assets/FeatureIcons/twitter.svg",
            "url": "/id/resize-for-twitter"
        },
        {
            "name": "Ubah Ukuran Untuk Whatsapp",
            "description": "Ubah Ukuran Video Untuk Whatsapp",
            "color": "#21A218",
            "icon": "/assets/FeatureIcons/whatsapp.svg",
            "url": "/id/resize-for-whatsapp"
        },
        {
            "name": "Ubah Ukuran Untuk Youtube",
            "description": "Ubah Ukuran Video Untuk Youtube",
            "color": "#FF0000",
            "icon": "/assets/FeatureIcons/youtube.svg",
            "url": "/id/resize-for-youtube"
        }
    ],
    "StructuredDataWebsite": {
        "@type": "WebSite",
        "name": "appscms",
        "alternateName": "appscms",
        "url": "www.appscms.com"
    },
    "StructuredDataorganization": {
        "@type": "Organization",
        "url": "http://www.appscms.com",
        "logo": "http://www.example.com/images/logo.png"
    }
}